dataselectors/__init__.py
dataselectors/__version__.py
dataselectors/base.py
dataselectors/selectors.py
dataselectors/utils.py
dataselectors-0.1.0.dist-info/LICENSE
dataselectors-0.1.0.dist-info/WHEEL
dataselectors-0.1.0.dist-info/METADATA
dataselectors-0.1.0.dist-info/RECORD
