Metadata-Version: 2.1
Name: dataselectors
Version: 0.1.0
Summary: Data selectors for Pandas dataframes
Keywords: Data selectors,data selection,types
Author-email: Robbert Harms <robbert@xkls.nl>
Requires-Python: >=3.12
Classifier: Development Status :: 5 - Production/Stable
Classifier: Intended Audience :: Science/Research
Classifier: Natural Language :: English
Classifier: License :: OSI Approved :: GNU Lesser General Public License v3 (LGPLv3)
Classifier: Programming Language :: Python :: 3.12
Requires-Dist: pandas~=2.2.2
Requires-Dist: numpy~=2.1.1
Requires-Dist: sphinx~=8.0.2 ; extra == "doc"
Requires-Dist: pytest~=8.3.3 ; extra == "test"
Requires-Dist: pytest-check~=2.4.1 ; extra == "test"
Requires-Dist: pytest-cov~=5.0.0 ; extra == "test"
Requires-Dist: pytest-html~=4.1.1 ; extra == "test"
Requires-Dist: tox~=4.18.1 ; extra == "test"
Provides-Extra: doc
Provides-Extra: test
